[
{"name": "001_buena_vista_park", "caption": "Buena Vista Park"},
{"name": "002_buena_vista_park", "caption": "Buena Vista Park"},
{"name": "003_buena_vista_park", "caption": "Buena Vista Park"},
{"name": "004_buena_vista_park", "caption": "Buena Vista Park"},
{"name": "005_buena_vista_park", "caption": "Buena Vista Park"},
{"name": "006_cool_flower_box", "caption": "Cool flower box"},
{"name": "007_sushi", "caption": "We had a delicious sushi feast at the restaurant Emily and Ed go to weekly"},
{"name": "008_pancakes", "caption": "yum"},
{"name": "010_mural", "caption": ""},
{"name": "011_glen_park_view_night", "caption": "View from Glen Park at night"},
{"name": "012_staples", "caption": "rusted staples on a utility pole"},
{"name": "013_mural", "caption": ""},
{"name": "014_wagon", "caption": ""},
{"name": "015_wagon", "caption": ""},
{"name": "016_mural", "caption": ""},
{"name": "017_mural", "caption": ""},
{"name": "018_beetle", "caption": ""},
{"name": "019_beater", "caption": ""},
{"name": "020_swing", "caption": "Swing dancing in Golden Gate Park"},
{"name": "021_swing", "caption": "Swing dancing in Golden Gate Park"},
{"name": "022_swing", "caption": "Swing dancing in Golden Gate Park"},
{"name": "023_leaf", "caption": "Giant leaves"},
{"name": "030_burma_superstar", "caption": "Burma Superstar in Oakland"},
{"name": "031_burma_superstar", "caption": "very delicious"},
{"name": "032_ocean", "caption": "Walked out to the ocean"},
{"caption": "Local Jazz/Funk masters Supercollider at The Laughing Goat", "name": "040_supercollider"},
{"name": "051_a-basin", "caption": "Lew and I skiied A-Basin May 27th"},
{"name": "052_a-basin", "caption": "I had never skiied that late in the season before"},
{"name": "053_a-basin", "caption": ""},
{"name": "054_lew", "caption": ""},
{"name": "056_lew", "caption": ""},
{"name": "057_lew", "caption": ""},
{"name": "058_a-basin", "caption": ""},
{"name": "059_a-basin", "caption": "You can see both Keystone and Breckenridge if you stand in the right spots"}
]
